[
  {
    "name": "notes",
    "contents": [
      {
        "content": "Architecture.md",
        "link": "notes/Architecture"
      }
    ],
    "subsections": [
  {
    "name": "microservices",
    "contents": [
      {
        "content": "api_gateway.md",
        "link": "notes/microservices/api_gateway"
      },
      {
        "content": "centralized_configuration.md",
        "link": "notes/microservices/centralized_configuration"
      },
      {
        "content": "circuit_breaker.md",
        "link": "notes/microservices/circuit_breaker"
      },
      {
        "content": "distributed_tracing.md",
        "link": "notes/microservices/distributed_tracing"
      },
      {
        "content": "feign.md",
        "link": "notes/microservices/feign"
      },
      {
        "content": "naming_server.md",
        "link": "notes/microservices/naming_server"
      },
      {
        "content": "ports_std.md",
        "link": "notes/microservices/ports_std"
      }
    ],
    "subsections": []
  }
,
  {
    "name": "ubuntu",
    "contents": [
      {
        "content": "ssh_key.md",
        "link": "notes/ubuntu/ssh_key"
      }
    ],
    "subsections": [
  {
    "name": "conf",
    "contents": [
      {
        "content": "ubuntu_conf.sh",
        "link": "notes/ubuntu/conf/ubuntu_conf"
      },
      {
        "content": "uninstall_ubuntu_conf.sh",
        "link": "notes/ubuntu/conf/uninstall_ubuntu_conf"
      }
    ],
    "subsections": []
  }

    ]
  }

    ]
  }
]
