[
  {
    "name": "notes",
    "contents": [],
    "subsections": [
  {
    "name": "ubuntu",
    "contents": [
      {
        "content": "ssh_key.md",
        "link": "notes/ubuntu/ssh_key"
      }
    ],
    "subsections": [
  {
    "name": "conf",
    "contents": [
      {
        "content": "ubuntu_conf.sh",
        "link": "notes/ubuntu/conf/ubuntu_conf"
      },
      {
        "content": "uninstall_ubuntu_conf.sh",
        "link": "notes/ubuntu/conf/uninstall_ubuntu_conf"
      }
    ],
    "subsections": []
  }

    ]
  }

    ]
  }
]
